flybase_mcp_server/__init__.py
flybase_mcp_server/__main__.py
flybase_mcp_server/data/gene_symbols_fbgn_ids.csv
flybase_mcp_server-0.1.1.dist-info/licenses/LICENSE.txt
flybase_mcp_server-0.1.1.dist-info/METADATA
flybase_mcp_server-0.1.1.dist-info/WHEEL
flybase_mcp_server-0.1.1.dist-info/entry_points.txt
flybase_mcp_server-0.1.1.dist-info/top_level.txt
flybase_mcp_server-0.1.1.dist-info/RECORD
